foxbit/client/__init__.py
foxbit/frame/__init__.py
foxbit-0.0.12.dist-info/LICENSE
foxbit-0.0.12.dist-info/METADATA
foxbit-0.0.12.dist-info/WHEEL
foxbit-0.0.12.dist-info/top_level.txt
foxbit-0.0.12.dist-info/RECORD
