Metadata-Version: 2.1
Name: foxbit
Version: 0.0.12
Summary: A python client for foxbit exchange API
Home-page: https://gitlab.com/qlrddev/foxbit/
Author: qlrd
Author-email: qlrddev@gmail.com
Maintainer: qlrd
Maintainer-email: qlrddev@gmail.com
License: Apache License Version 2.0
Keywords: websocket,API,exchange,foxbit
Platform: UNKNOWN
Classifier: Development Status :: 1 - Planning
Classifier: Topic :: Software Development :: Libraries :: Python Modules
Classifier: Intended Audience :: Developers
Classifier: Natural Language :: Portuguese (Brazilian)
Classifier: Programming Language :: Python :: 3.10
License-File: LICENSE
Requires-Dist: websocket-client (>=1.2.3)
Provides-Extra: test
Requires-Dist: tox-wheel (>=0.7.0) ; extra == 'test'
Requires-Dist: pytest (>=6.2.5) ; extra == 'test'
Requires-Dist: pytest-cov (>=3.0.0) ; extra == 'test'
Requires-Dist: flake8 (>=4.0.1) ; extra == 'test'
Requires-Dist: coverage (>=6.3.0) ; extra == 'test'
